LICENSE.txt
MANIFEST.in
readme.md
setup.cfg
setup.py
pymulticrypt/__init__.py
pymulticrypt/pymulticrypt.py
pymulticrypt.egg-info/PKG-INFO
pymulticrypt.egg-info/SOURCES.txt
pymulticrypt.egg-info/dependency_links.txt
pymulticrypt.egg-info/top_level.txt