Metadata-Version: 2.1
Name: pymulticrypt
Version: 1.2
Summary: Python Module for secure End-2-End encryption using the Multicrypt algorithm made by me
Home-page: https://github.com/AbhayTr/PyMulticrypt
Author: Abhay Tripathi
Author-email: abhay.triipathi@gmail.com
License: MIT
Download-URL: https://github.com/AbhayTr/PyMulticrypt/archive/v1.2.tar.gz
Keywords: PyMulticrypt,Encryption,Asymmetric Encryption,Symmetric Encryption,End2End Encryption,End2End,Signal Protocol
Platform: UNKNOWN
Classifier: Development Status :: 5 - Production/Stable
Classifier: Intended Audience :: Developers
Classifier: Topic :: Software Development :: Build Tools
Classifier: License :: OSI Approved :: MIT License
Classifier: Programming Language :: Python :: 2
Classifier: Programming Language :: Python :: 3
Classifier: Programming Language :: Python :: 3.4
Classifier: Programming Language :: Python :: 3.5
Classifier: Programming Language :: Python :: 3.6
